{
  "name": "Tasks",
  "icon": "✅",
  "description": "Aurora smart-home launch — every phase, epic, task, and sub-task with rolled-up effort and dependencies.",
  "schema": {
    "title": { "type": "title" },
    "phase": {
      "type": "select",
      "options": [
        { "name": "Discovery", "color": "purple" },
        { "name": "Build", "color": "blue" },
        { "name": "GTM", "color": "orange" },
        { "name": "Launch", "color": "red" },
        { "name": "Post-launch", "color": "green" }
      ]
    },
    "department": {
      "type": "select",
      "options": [
        { "name": "Engineering", "color": "blue" },
        { "name": "Marketing", "color": "orange" },
        { "name": "Sales", "color": "yellow" },
        { "name": "Operations", "color": "green" },
        { "name": "Finance", "color": "purple" },
        { "name": "People", "color": "pink" }
      ]
    },
    "status": {
      "type": "select",
      "options": [
        { "name": "Backlog", "color": "gray" },
        { "name": "In Progress", "color": "blue" },
        { "name": "Blocked", "color": "red" },
        { "name": "Review", "color": "yellow" },
        { "name": "Done", "color": "green" }
      ]
    },
    "priority": {
      "type": "select",
      "options": [
        { "name": "Low", "color": "gray" },
        { "name": "Medium", "color": "yellow" },
        { "name": "High", "color": "orange" },
        { "name": "Critical", "color": "red" }
      ]
    },
    "owner": { "type": "text" },
    "start": { "type": "date" },
    "due": { "type": "date" },
    "effort_days": { "type": "number" },
    "blocked_by": { "type": "row_ref", "ref_db": "Tasks.db.json" }
  },
  "views": [
    {
      "name": "Board",
      "type": "board",
      "group_by": "status",
      "visible_properties": ["title", "phase", "department", "priority", "owner", "due"],
      "sorts": [],
      "filters": []
    },
    {
      "name": "By Phase",
      "type": "table",
      "group_by": "phase",
      "visible_properties": ["title", "phase", "department", "status", "priority", "owner", "start", "due", "effort_days"],
      "property_widths": { "title": 360, "owner": 150 },
      "sorts": [{ "property": "phase", "direction": "asc" }],
      "filters": []
    },
    {
      "name": "Calendar",
      "type": "calendar",
      "date_property": "due",
      "visible_properties": ["title", "department", "status", "owner"],
      "sorts": [],
      "filters": []
    },
    {
      "name": "All Tasks",
      "type": "table",
      "visible_properties": ["title", "phase", "department", "status", "priority", "owner", "start", "due", "effort_days", "blocked_by"],
      "property_widths": { "title": 360, "owner": 150 },
      "sorts": [{ "property": "due", "direction": "asc" }],
      "filters": []
    }
  ],
  "rows": [
    {
      "id": "row_1746000000000_0",
      "title": "Phase 1 — Discovery",
      "phase": "Discovery",
      "department": "Operations",
      "status": "Done",
      "priority": "High",
      "owner": "Priya Raman",
      "start": "2026-05-04",
      "due": "2026-06-12",
      "effort_days": "__sum__"
    },
    {
      "id": "row_1746000000000_1",
      "title": "Market & customer research",
      "phase": "Discovery",
      "department": "Marketing",
      "status": "Done",
      "priority": "High",
      "owner": "Daniel Okafor",
      "start": "2026-05-04",
      "due": "2026-05-22",
      "effort_days": "__sum__",
      "_parent_id": "row_1746000000000_0"
    },
    {
      "id": "row_1746000000000_2",
      "title": "Run 12 customer discovery interviews",
      "phase": "Discovery",
      "department": "Marketing",
      "status": "Done",
      "priority": "High",
      "owner": "Daniel Okafor",
      "start": "2026-05-04",
      "due": "2026-05-15",
      "effort_days": 8,
      "_parent_id": "row_1746000000000_1"
    },
    {
      "id": "row_1746000000000_3",
      "title": "Competitive teardown of 5 rival hubs",
      "phase": "Discovery",
      "department": "Marketing",
      "status": "Done",
      "priority": "Medium",
      "owner": "Sofia Marino",
      "start": "2026-05-11",
      "due": "2026-05-20",
      "effort_days": 5,
      "_parent_id": "row_1746000000000_1"
    },
    {
      "id": "row_1746000000000_4",
      "title": "Synthesize findings into a positioning brief",
      "phase": "Discovery",
      "department": "Marketing",
      "status": "Done",
      "priority": "Medium",
      "owner": "Daniel Okafor",
      "start": "2026-05-20",
      "due": "2026-05-22",
      "effort_days": 3,
      "_parent_id": "row_1746000000000_1"
    },
    {
      "id": "row_1746000000000_5",
      "title": "Technical feasibility & architecture spike",
      "phase": "Discovery",
      "department": "Engineering",
      "status": "Done",
      "priority": "Critical",
      "owner": "Mei-Ling Chen",
      "start": "2026-05-11",
      "due": "2026-06-05",
      "effort_days": "__sum__",
      "_parent_id": "row_1746000000000_0"
    },
    {
      "id": "row_1746000000000_6",
      "title": "Evaluate Zigbee vs. Matter radio stack",
      "phase": "Discovery",
      "department": "Engineering",
      "status": "Done",
      "priority": "Critical",
      "owner": "Mei-Ling Chen",
      "start": "2026-05-11",
      "due": "2026-05-25",
      "effort_days": 9,
      "_parent_id": "row_1746000000000_5"
    },
    {
      "id": "row_1746000000000_7",
      "title": "Prototype companion-app sync engine",
      "phase": "Discovery",
      "department": "Engineering",
      "status": "Done",
      "priority": "High",
      "owner": "Aleksandr Volkov",
      "start": "2026-05-18",
      "due": "2026-06-05",
      "effort_days": 12,
      "_parent_id": "row_1746000000000_5"
    },
    {
      "id": "row_1746000000000_8",
      "title": "Business case & pricing model",
      "phase": "Discovery",
      "department": "Finance",
      "status": "Done",
      "priority": "High",
      "owner": "Hannah Bergström",
      "start": "2026-05-25",
      "due": "2026-06-12",
      "effort_days": "__sum__",
      "_parent_id": "row_1746000000000_0"
    },
    {
      "id": "row_1746000000000_9",
      "title": "Build unit-economics model",
      "phase": "Discovery",
      "department": "Finance",
      "status": "Done",
      "priority": "High",
      "owner": "Hannah Bergström",
      "start": "2026-05-25",
      "due": "2026-06-04",
      "effort_days": 6,
      "_parent_id": "row_1746000000000_8"
    },
    {
      "id": "row_1746000000000_10",
      "title": "Set launch-price tiers and approve margins",
      "phase": "Discovery",
      "department": "Finance",
      "status": "Done",
      "priority": "Medium",
      "owner": "Hannah Bergström",
      "start": "2026-06-04",
      "due": "2026-06-12",
      "effort_days": 4,
      "_parent_id": "row_1746000000000_8"
    },
    {
      "id": "row_1746000000000_11",
      "title": "Phase 2 — Build",
      "phase": "Build",
      "department": "Engineering",
      "status": "In Progress",
      "priority": "Critical",
      "owner": "Mei-Ling Chen",
      "start": "2026-06-15",
      "due": "2026-08-21",
      "effort_days": "__sum__"
    },
    {
      "id": "row_1746000000000_12",
      "title": "Hardware design & DFM",
      "phase": "Build",
      "department": "Engineering",
      "status": "In Progress",
      "priority": "Critical",
      "owner": "Aleksandr Volkov",
      "start": "2026-06-15",
      "due": "2026-08-07",
      "effort_days": "__sum__",
      "_parent_id": "row_1746000000000_11"
    },
    {
      "id": "row_1746000000000_13",
      "title": "Finalize PCB layout for the hub",
      "phase": "Build",
      "department": "Engineering",
      "status": "Done",
      "priority": "Critical",
      "owner": "Aleksandr Volkov",
      "start": "2026-06-15",
      "due": "2026-07-03",
      "effort_days": 14,
      "_parent_id": "row_1746000000000_12",
      "blocked_by": "Tasks.db.json||row_1746000000000_6"
    },
    {
      "id": "row_1746000000000_14",
      "title": "Injection-mold enclosure tooling kickoff",
      "phase": "Build",
      "department": "Operations",
      "status": "In Progress",
      "priority": "High",
      "owner": "Carlos Mendes",
      "start": "2026-07-06",
      "due": "2026-08-07",
      "effort_days": 18,
      "_parent_id": "row_1746000000000_12",
      "blocked_by": "Tasks.db.json||row_1746000000000_13"
    },
    {
      "id": "row_1746000000000_15",
      "title": "Pass EMC and safety pre-certification",
      "phase": "Build",
      "department": "Engineering",
      "status": "Blocked",
      "priority": "Critical",
      "owner": "Mei-Ling Chen",
      "start": "2026-07-20",
      "due": "2026-08-05",
      "effort_days": 10,
      "_parent_id": "row_1746000000000_12",
      "blocked_by": "Tasks.db.json||row_1746000000000_13"
    },
    {
      "id": "row_1746000000000_16",
      "title": "Firmware & companion app",
      "phase": "Build",
      "department": "Engineering",
      "status": "In Progress",
      "priority": "Critical",
      "owner": "Mei-Ling Chen",
      "start": "2026-06-15",
      "due": "2026-08-21",
      "effort_days": "__sum__",
      "_parent_id": "row_1746000000000_11"
    },
    {
      "id": "row_1746000000000_17",
      "title": "Implement Matter pairing flow",
      "phase": "Build",
      "department": "Engineering",
      "status": "In Progress",
      "priority": "Critical",
      "owner": "Aleksandr Volkov",
      "start": "2026-06-15",
      "due": "2026-07-10",
      "effort_days": "__sum__",
      "_parent_id": "row_1746000000000_16",
      "blocked_by": "Tasks.db.json||row_1746000000000_7"
    },
    {
      "id": "row_1746000000000_18",
      "title": "Onboarding wizard UI",
      "phase": "Build",
      "department": "Engineering",
      "status": "Done",
      "priority": "High",
      "owner": "Yuki Tanaka",
      "start": "2026-06-15",
      "due": "2026-06-30",
      "effort_days": 8,
      "_parent_id": "row_1746000000000_17"
    },
    {
      "id": "row_1746000000000_19",
      "title": "Cloud account-linking service",
      "phase": "Build",
      "department": "Engineering",
      "status": "In Progress",
      "priority": "Critical",
      "owner": "Aleksandr Volkov",
      "start": "2026-06-25",
      "due": "2026-07-10",
      "effort_days": 9,
      "_parent_id": "row_1746000000000_17"
    },
    {
      "id": "row_1746000000000_20",
      "title": "Build automations & scenes engine",
      "phase": "Build",
      "department": "Engineering",
      "status": "In Progress",
      "priority": "High",
      "owner": "Yuki Tanaka",
      "start": "2026-07-10",
      "due": "2026-08-07",
      "effort_days": 15,
      "_parent_id": "row_1746000000000_16"
    },
    {
      "id": "row_1746000000000_21",
      "title": "Localize app into 6 languages",
      "phase": "Build",
      "department": "Engineering",
      "status": "Backlog",
      "priority": "Medium",
      "owner": "Yuki Tanaka",
      "start": "2026-08-03",
      "due": "2026-08-21",
      "effort_days": 7,
      "_parent_id": "row_1746000000000_16"
    },
    {
      "id": "row_1746000000000_22",
      "title": "Supply chain & manufacturing setup",
      "phase": "Build",
      "department": "Operations",
      "status": "In Progress",
      "priority": "High",
      "owner": "Carlos Mendes",
      "start": "2026-07-01",
      "due": "2026-08-21",
      "effort_days": "__sum__",
      "_parent_id": "row_1746000000000_11"
    },
    {
      "id": "row_1746000000000_23",
      "title": "Qualify two contract manufacturers",
      "phase": "Build",
      "department": "Operations",
      "status": "In Progress",
      "priority": "High",
      "owner": "Carlos Mendes",
      "start": "2026-07-01",
      "due": "2026-07-25",
      "effort_days": 11,
      "_parent_id": "row_1746000000000_22"
    },
    {
      "id": "row_1746000000000_24",
      "title": "Lock component sourcing for first 20k units",
      "phase": "Build",
      "department": "Operations",
      "status": "Backlog",
      "priority": "High",
      "owner": "Carlos Mendes",
      "start": "2026-07-25",
      "due": "2026-08-21",
      "effort_days": 13,
      "_parent_id": "row_1746000000000_22",
      "blocked_by": "Tasks.db.json||row_1746000000000_23"
    },
    {
      "id": "row_1746000000000_25",
      "title": "Phase 3 — Go-to-market",
      "phase": "GTM",
      "department": "Marketing",
      "status": "In Progress",
      "priority": "High",
      "owner": "Daniel Okafor",
      "start": "2026-08-03",
      "due": "2026-09-18",
      "effort_days": "__sum__"
    },
    {
      "id": "row_1746000000000_26",
      "title": "Brand & creative",
      "phase": "GTM",
      "department": "Marketing",
      "status": "In Progress",
      "priority": "High",
      "owner": "Sofia Marino",
      "start": "2026-08-03",
      "due": "2026-09-04",
      "effort_days": "__sum__",
      "_parent_id": "row_1746000000000_25"
    },
    {
      "id": "row_1746000000000_27",
      "title": "Produce launch film and product photography",
      "phase": "GTM",
      "department": "Marketing",
      "status": "In Progress",
      "priority": "High",
      "owner": "Sofia Marino",
      "start": "2026-08-03",
      "due": "2026-08-28",
      "effort_days": 16,
      "_parent_id": "row_1746000000000_26",
      "blocked_by": "Tasks.db.json||row_1746000000000_14"
    },
    {
      "id": "row_1746000000000_28",
      "title": "Build the marketing site and pre-order page",
      "phase": "GTM",
      "department": "Marketing",
      "status": "Backlog",
      "priority": "High",
      "owner": "Sofia Marino",
      "start": "2026-08-17",
      "due": "2026-09-04",
      "effort_days": 9,
      "_parent_id": "row_1746000000000_26"
    },
    {
      "id": "row_1746000000000_29",
      "title": "Channel & sales enablement",
      "phase": "GTM",
      "department": "Sales",
      "status": "Backlog",
      "priority": "High",
      "owner": "James Whitfield",
      "start": "2026-08-24",
      "due": "2026-09-18",
      "effort_days": "__sum__",
      "_parent_id": "row_1746000000000_25"
    },
    {
      "id": "row_1746000000000_30",
      "title": "Sign 3 national retail partners",
      "phase": "GTM",
      "department": "Sales",
      "status": "Backlog",
      "priority": "Critical",
      "owner": "James Whitfield",
      "start": "2026-08-24",
      "due": "2026-09-12",
      "effort_days": 12,
      "_parent_id": "row_1746000000000_29"
    },
    {
      "id": "row_1746000000000_31",
      "title": "Train field sales on the demo script",
      "phase": "GTM",
      "department": "Sales",
      "status": "Backlog",
      "priority": "Medium",
      "owner": "Nadia Haddad",
      "start": "2026-09-08",
      "due": "2026-09-18",
      "effort_days": 5,
      "_parent_id": "row_1746000000000_29",
      "blocked_by": "Tasks.db.json||row_1746000000000_30"
    },
    {
      "id": "row_1746000000000_32",
      "title": "Phase 4 — Launch",
      "phase": "Launch",
      "department": "Operations",
      "status": "Backlog",
      "priority": "Critical",
      "owner": "Priya Raman",
      "start": "2026-09-21",
      "due": "2026-10-09",
      "effort_days": "__sum__"
    },
    {
      "id": "row_1746000000000_33",
      "title": "Final mass-production run & QA",
      "phase": "Launch",
      "department": "Operations",
      "status": "Backlog",
      "priority": "Critical",
      "owner": "Carlos Mendes",
      "start": "2026-09-21",
      "due": "2026-10-02",
      "effort_days": 9,
      "_parent_id": "row_1746000000000_32",
      "blocked_by": "Tasks.db.json||row_1746000000000_24"
    },
    {
      "id": "row_1746000000000_34",
      "title": "Stock distribution centers and retail partners",
      "phase": "Launch",
      "department": "Operations",
      "status": "Backlog",
      "priority": "High",
      "owner": "Carlos Mendes",
      "start": "2026-09-28",
      "due": "2026-10-07",
      "effort_days": 6,
      "_parent_id": "row_1746000000000_32",
      "blocked_by": "Tasks.db.json||row_1746000000000_33"
    },
    {
      "id": "row_1746000000000_35",
      "title": "Launch-day press and PR push",
      "phase": "Launch",
      "department": "Marketing",
      "status": "Backlog",
      "priority": "Critical",
      "owner": "Daniel Okafor",
      "start": "2026-10-05",
      "due": "2026-10-09",
      "effort_days": 4,
      "_parent_id": "row_1746000000000_32",
      "blocked_by": "Tasks.db.json||row_1746000000000_28"
    },
    {
      "id": "row_1746000000000_36",
      "title": "Stand up the launch-week support war room",
      "phase": "Launch",
      "department": "People",
      "status": "Backlog",
      "priority": "High",
      "owner": "Olivia Grant",
      "start": "2026-10-01",
      "due": "2026-10-09",
      "effort_days": 5,
      "_parent_id": "row_1746000000000_32"
    },
    {
      "id": "row_1746000000000_37",
      "title": "Phase 5 — Post-launch",
      "phase": "Post-launch",
      "department": "Operations",
      "status": "Backlog",
      "priority": "Medium",
      "owner": "Priya Raman",
      "start": "2026-10-12",
      "due": "2026-10-30",
      "effort_days": "__sum__"
    },
    {
      "id": "row_1746000000000_38",
      "title": "Run the 2-week launch retrospective",
      "phase": "Post-launch",
      "department": "Operations",
      "status": "Backlog",
      "priority": "Medium",
      "owner": "Priya Raman",
      "start": "2026-10-12",
      "due": "2026-10-23",
      "effort_days": 4,
      "_parent_id": "row_1746000000000_37"
    },
    {
      "id": "row_1746000000000_39",
      "title": "Ship first over-the-air firmware update",
      "phase": "Post-launch",
      "department": "Engineering",
      "status": "Backlog",
      "priority": "High",
      "owner": "Yuki Tanaka",
      "start": "2026-10-19",
      "due": "2026-10-30",
      "effort_days": 7,
      "_parent_id": "row_1746000000000_37"
    },
    {
      "id": "row_1746000000000_40",
      "title": "Analyze week-one sell-through and returns",
      "phase": "Post-launch",
      "department": "Finance",
      "status": "Backlog",
      "priority": "Medium",
      "owner": "Hannah Bergström",
      "start": "2026-10-12",
      "due": "2026-10-26",
      "effort_days": 5,
      "_parent_id": "row_1746000000000_37"
    },
    {
      "id": "row_1746000000000_41",
      "title": "Open week-one customer-feedback loop with support",
      "phase": "Post-launch",
      "department": "People",
      "status": "Backlog",
      "priority": "Medium",
      "owner": "Olivia Grant",
      "start": "2026-10-12",
      "due": "2026-10-28",
      "effort_days": 4,
      "_parent_id": "row_1746000000000_37"
    }
  ]
}
